{
  "invoices": [
    {
      "user_identity_token": "encrypted_token_here",
      "business_identity_token": "encrypted_business_token_here",
      "invoice_number": "INV20250001",
      "amount": 25.5,
      "due_date": "2025-01-27",
      "status": "paid",
      "created_at": "2025-01-20T10:30:00Z",
      "weekday": "Monday"
    },
    {
      "user_identity_token": "encrypted_token_here",
      "business_identity_token": "encrypted_business_token_here",
      "invoice_number": "INV20250002",
      "amount": 45,
      "due_date": "2025-01-28",
      "status": "paid",
      "created_at": "2025-01-21T14:20:00Z",
      "weekday": "Tuesday"
    },
    {
      "user_identity_token": "encrypted_token_here",
      "business_identity_token": "encrypted_business_token_here",
      "invoice_number": "INV20250003",
      "amount": 12.75,
      "due_date": "2025-01-28",
      "status": "paid",
      "created_at": "2025-01-21T16:45:00Z",
      "weekday": "Tuesday"
    },
    {
      "user_identity_token": "encrypted_token_here",
      "business_identity_token": "encrypted_business_token_here",
      "invoice_number": "INV20250004",
      "amount": 67.25,
      "due_date": "2025-01-29",
      "status": "paid",
      "created_at": "2025-01-22T09:15:00Z",
      "weekday": "Wednesday"
    },
    {
      "user_identity_token": "encrypted_token_here",
      "business_identity_token": "encrypted_business_token_here",
      "invoice_number": "INV20250005",
      "amount": 33.8,
      "due_date": "2025-01-29",
      "status": "pending",
      "created_at": "2025-01-22T11:30:00Z",
      "weekday": "Wednesday"
    },
    {
      "user_identity_token": "encrypted_token_here",
      "business_identity_token": "encrypted_business_token_here",
      "invoice_number": "INV20250006",
      "amount": 55.25,
      "due_date": "2025-02-01",
      "status": "paid",
      "created_at": "2025-01-25T15:20:00Z",
      "weekday": "Saturday"
    },
    {
      "user_identity_token": "encrypted_token_here",
      "business_identity_token": "encrypted_business_token_here",
      "invoice_number": "INV20250007",
      "amount": 78.9,
      "due_date": "2025-02-02",
      "status": "paid",
      "created_at": "2025-01-26T12:10:00Z",
      "weekday": "Sunday"
    },
    {
      "user_identity_token": "encrypted_token_here",
      "business_identity_token": "encrypted_business_token_here",
      "invoice_number": "INV20250008",
      "amount": 89,
      "due_date": "2025-07-24",
      "status": "paid",
      "created_at": "2025-07-17T20:09:32.477Z",
      "weekday": "Friday"
    },
    {
      "user_identity_token": "encrypted_token_here",
      "business_identity_token": "encrypted_business_token_here",
      "invoice_number": "INV20250009",
      "amount": 89,
      "due_date": "2025-07-24",
      "status": "paid",
      "created_at": "2025-07-17T20:09:44.475Z",
      "weekday": "Friday"
    },
    {
      "user_identity_token": "encrypted_token_here",
      "business_identity_token": "encrypted_business_token_here",
      "invoice_number": "INV20250010",
      "amount": 66,
      "due_date": "2025-07-24",
      "status": "paid",
      "created_at": "2025-07-17T20:15:40.038Z",
      "weekday": "Friday"
    },
    {
      "user_identity_token": "demo_user_token",
      "business_identity_token": "demo_business_token",
      "invoice_number": "INV20250011",
      "amount": 24,
      "due_date": "2025-07-24",
      "status": "paid",
      "created_at": "2025-07-17T22:37:43.174Z",
      "weekday": "Friday"
    },
    {
      "user_identity_token": "demo_user_token",
      "business_identity_token": "demo_business_token",
      "invoice_number": "INV20250012",
      "amount": 3,
      "due_date": "2025-07-25",
      "status": "paid",
      "created_at": "2025-07-18T07:56:46.539Z",
      "weekday": "Friday"
    },
    {
      "user_identity_token": "demo_user_token",
      "business_identity_token": "demo_business_token",
      "invoice_number": "INV20250013",
      "amount": 2,
      "due_date": "2025-07-25",
      "status": "paid",
      "created_at": "2025-07-18T08:03:12.795Z",
      "weekday": "Friday"
    },
    {
      "user_identity_token": "demo_user_token",
      "business_identity_token": "demo_business_token",
      "invoice_number": "INV20250014",
      "amount": 2,
      "due_date": "2025-07-25",
      "status": "paid",
      "created_at": "2025-07-18T08:50:31.907Z",
      "weekday": "Friday"
    },
    {
      "user_identity_token": "demo_user_token",
      "business_identity_token": "demo_business_token",
      "invoice_number": "INV20250015",
      "amount": 5,
      "due_date": "2025-07-25",
      "status": "paid",
      "created_at": "2025-07-18T11:58:09.361Z",
      "weekday": "Friday"
    }
  ]
}